bottle_swagger/__init__.py
bottle_swagger/vendor/swagger-ui-4.17.1-dist/favicon-16x16.png
bottle_swagger/vendor/swagger-ui-4.17.1-dist/favicon-32x32.png
bottle_swagger/vendor/swagger-ui-4.17.1-dist/index.css
bottle_swagger/vendor/swagger-ui-4.17.1-dist/index.html
bottle_swagger/vendor/swagger-ui-4.17.1-dist/index.html.st
bottle_swagger/vendor/swagger-ui-4.17.1-dist/oauth2-redirect.html
bottle_swagger/vendor/swagger-ui-4.17.1-dist/swagger-initializer.js
bottle_swagger/vendor/swagger-ui-4.17.1-dist/swagger-ui-bundle.js
bottle_swagger/vendor/swagger-ui-4.17.1-dist/swagger-ui-bundle.js.map
bottle_swagger/vendor/swagger-ui-4.17.1-dist/swagger-ui-es-bundle-core.js
bottle_swagger/vendor/swagger-ui-4.17.1-dist/swagger-ui-es-bundle-core.js.map
bottle_swagger/vendor/swagger-ui-4.17.1-dist/swagger-ui-es-bundle.js
bottle_swagger/vendor/swagger-ui-4.17.1-dist/swagger-ui-es-bundle.js.map
bottle_swagger/vendor/swagger-ui-4.17.1-dist/swagger-ui-standalone-preset.js
bottle_swagger/vendor/swagger-ui-4.17.1-dist/swagger-ui-standalone-preset.js.map
bottle_swagger/vendor/swagger-ui-4.17.1-dist/swagger-ui.css
bottle_swagger/vendor/swagger-ui-4.17.1-dist/swagger-ui.css.map
bottle_swagger/vendor/swagger-ui-4.17.1-dist/swagger-ui.js
bottle_swagger/vendor/swagger-ui-4.17.1-dist/swagger-ui.js.map
bottle_swagger_2-2.0.15.dist-info/LICENSE
bottle_swagger_2-2.0.15.dist-info/METADATA
bottle_swagger_2-2.0.15.dist-info/WHEEL
bottle_swagger_2-2.0.15.dist-info/top_level.txt
bottle_swagger_2-2.0.15.dist-info/RECORD
