Metadata-Version: 2.1
Name: bottle-swagger-2
Version: 2.0.15
Summary: Swagger Integration for Bottle
Home-page: https://github.com/cope-systems/bottle-swagger
Author: Robert Cope, Charles Blaxland
Author-email: robert@copesystems.com, charles.blaxland@gmail.com
License: MIT
Download-URL: https://github.com/cope-systems/bottle-swagger/archive/v2.0.15.tar.gz
Platform: any
Classifier: Environment :: Web Environment
Classifier: Environment :: Plugins
Classifier: Framework :: Bottle
Classifier: Intended Audience :: Developers
Classifier: License :: OSI Approved :: MIT License
Classifier: Operating System :: OS Independent
Classifier: Programming Language :: Python
Classifier: Programming Language :: Python :: 3.5
Classifier: Programming Language :: Python :: 3.6
Classifier: Programming Language :: Python :: 3.7
Classifier: Programming Language :: Python :: 3.8
Classifier: Topic :: Internet :: WWW/HTTP :: Dynamic Content
Classifier: Topic :: Software Development :: Libraries :: Python Modules
Requires-Dist: bottle
Requires-Dist: jsonschema (==3.2.0)
Requires-Dist: bravado-core
Requires-Dist: six
